tokyopopuchange.py
tokyopopuchange-1.0.1.dist-info/METADATA
tokyopopuchange-1.0.1.dist-info/WHEEL
tokyopopuchange-1.0.1.dist-info/entry_points.txt
tokyopopuchange-1.0.1.dist-info/top_level.txt
tokyopopuchange-1.0.1.dist-info/RECORD
